uml2django/__init__.py
uml2django/__main__.py
uml2django/argparser.py
uml2django/logger.py
uml2django/main.py
uml2django/settings.py
uml2django/templates.py
uml2django/cheetah_templates/prepare_database.tmpl
uml2django/cheetah_templates/app/urls.tmpl
uml2django/cheetah_templates/app/forms/ModelCreateForm.tmpl
uml2django/cheetah_templates/app/forms/ModelUpdateForm.tmpl
uml2django/cheetah_templates/app/models/BaseModel.tmpl
uml2django/cheetah_templates/app/models/Model.tmpl
uml2django/cheetah_templates/app/rest_api/ModelSerializer.tmpl
uml2django/cheetah_templates/app/rest_api/ModelViewSet.tmpl
uml2django/cheetah_templates/app/rest_api/router.tmpl
uml2django/cheetah_templates/app/templates/template_create.tmpl
uml2django/cheetah_templates/app/templates/template_delete.tmpl
uml2django/cheetah_templates/app/templates/template_detail.tmpl
uml2django/cheetah_templates/app/templates/template_list.tmpl
uml2django/cheetah_templates/app/templates/template_update.tmpl
uml2django/cheetah_templates/app/tests/ModelViewsTest.tmpl
uml2django/cheetah_templates/app/views/CreateView.tmpl
uml2django/cheetah_templates/app/views/DeleteView.tmpl
uml2django/cheetah_templates/app/views/DetailView.tmpl
uml2django/cheetah_templates/app/views/ListView.tmpl
uml2django/cheetah_templates/app/views/UpdateView.tmpl
uml2django/objects/DjangoModel.py
uml2django/objects/DjangoModelField.py
uml2django/objects/__init__.py
uml2django/parsers/__init__.py
uml2django/parsers/django/__init__.py
uml2django/parsers/django/configure_corsheaders.py
uml2django/parsers/django/generate_prepare_database.py
uml2django/parsers/django/start_django_project.py
uml2django/parsers/files/__init__.py
uml2django/parsers/files/add_import_to_init_file.py
uml2django/parsers/files/enforce_is_valid_file.py
uml2django/parsers/files/file_reader.py
uml2django/parsers/files/file_writer.py
uml2django/parsers/files/get_substring_between_parenthesis.py
uml2django/parsers/files/load_data_from_puml_or_xmi.py
uml2django-0.0.8.dist-info/AUTHORS.rst
uml2django-0.0.8.dist-info/LICENSE.txt
uml2django-0.0.8.dist-info/METADATA
uml2django-0.0.8.dist-info/WHEEL
uml2django-0.0.8.dist-info/entry_points.txt
uml2django-0.0.8.dist-info/top_level.txt
uml2django-0.0.8.dist-info/RECORD
