Metadata-Version: 2.1
Name: uml2django
Version: 0.0.8
Summary: Generate Django code from PlantUML class diagrams.
Author-email: Joao Cunha <jvsdc1992@gmail.com>
License: THE SOFTWARE IS PROVIDED "AS IS", WITHOUT WARRANTY OF ANY KIND, EXPRESS OR IMPLIED.
Project-URL: Homepage, https://github.com/j-hanks/uml2django
Classifier: Development Status :: 2 - Pre-Alpha
Classifier: Programming Language :: Python :: 3
Classifier: Environment :: Console
Classifier: Framework :: Django
Classifier: Intended Audience :: Developers
Classifier: License :: Public Domain
Classifier: Operating System :: OS Independent
Classifier: Topic :: Software Development :: Code Generators
Requires-Python: >=3.8
License-File: LICENSE.txt
License-File: AUTHORS.rst
Requires-Dist: cheetah3
Requires-Dist: inflect
Requires-Dist: redbaron
Provides-Extra: dev
Requires-Dist: tox ; extra == 'dev'
